aipython/__init__.py
aipython/agentEnv.py
aipython/agentMiddle.py
aipython/agentTop.py
aipython/agents.py
aipython/cspConsistency.py
aipython/cspExamples.py
aipython/cspProblem.py
aipython/cspSLS.py
aipython/cspSearch.py
aipython/decnNetworks.py
aipython/learnBoosting.py
aipython/learnBoosting1.py
aipython/learnCoordinate.py
aipython/learnCrossValidation.py
aipython/learnCrossValidation_dashed.py
aipython/learnDT.py
aipython/learnEM.py
aipython/learnKMeans.py
aipython/learnLinear.py
aipython/learnLinearBSGD.py
aipython/learnNN.py
aipython/learnNN_characteristic.py
aipython/learnNoInputs.py
aipython/learnProblem.py
aipython/learnProblem_old.py
aipython/logicAssumables.py
aipython/logicBottomUp.py
aipython/logicProblem.py
aipython/logicTopDown.py
aipython/masMiniMax.py
aipython/masProblem.py
aipython/mdpExamples.py
aipython/mdpProblem.py
aipython/probDBN.py
aipython/probFactors.py
aipython/probGraphicalModels.py
aipython/probHMM.py
aipython/probMCMC.py
aipython/probStochSim.py
aipython/probVE.py
aipython/probVariables.py
aipython/pythonDemo.py
aipython/relnCollFilt.py
aipython/relnCollFilt_stats.py
aipython/rlFeatures.py
aipython/rlModelLearner.py
aipython/rlPlot.py
aipython/rlProblem.py
aipython/rlQLearner.py
aipython/rlQTest.py
aipython/rlSimpleEnv.py
aipython/rlSimpleGameFeatures.py
aipython/searchBranchAndBound.py
aipython/searchDepthFirst.py
aipython/searchGeneric.py
aipython/searchMPP.py
aipython/searchProblem.py
aipython/searchSolution.py
aipython/searchTest.py
aipython/stripsCSPPlanner.py
aipython/stripsForwardPlanner.py
aipython/stripsHeuristic.py
aipython/stripsPOP.py
aipython/stripsProblem.py
aipython/stripsRegressionPlanner.py
aipython/utilities.py
aispace2/__init__.py
aispace2/_version.py
aispace2/jupyter/__init__.py
aispace2/jupyter/stepdomwidget.py
aispace2/jupyter/bayes/__init__.py
aispace2/jupyter/bayes/bayes.py
aispace2/jupyter/bayes/bayesjsonbridge.py
aispace2-0.6.9.dist-info/DESCRIPTION.rst
aispace2-0.6.9.dist-info/METADATA
aispace2-0.6.9.dist-info/RECORD
aispace2-0.6.9.dist-info/WHEEL
aispace2-0.6.9.dist-info/metadata.json
aispace2-0.6.9.dist-info/top_level.txt
