Metadata-Version: 2.0
Name: aispace2
Version: 0.6.9
Summary: A Jupyter extension for the next-generation of AISpace
Home-page: https://aispace2.github.io/AISpace2/
Author: AISpace2
Author-email: info@aispace.org
License: UNKNOWN
Keywords: ipython,jupyter,widgets,artifical intelligence,education
Platform: UNKNOWN
Classifier: Development Status :: 4 - Beta
Classifier: Framework :: IPython
Classifier: Intended Audience :: Developers
Classifier: Intended Audience :: Science/Research
Classifier: Topic :: Multimedia :: Graphics
Classifier: Programming Language :: Python :: 3.3
Classifier: Programming Language :: Python :: 3.4
Classifier: Programming Language :: Python :: 3.5
Requires-Dist: ipywidgets (>=7.0.0)
Requires-Dist: matplotlib (>=2.0.0)
